djangocms_timer/cms_plugins.py
djangocms_timer/__init__.py
djangocms_timer/models.py
djangocms_timer/templates/djangocms_timer/timer.html
djangocms_timer-0.1.0.dist-info/WHEEL
djangocms_timer-0.1.0.dist-info/METADATA
djangocms_timer-0.1.0.dist-info/top_level.txt
djangocms_timer-0.1.0.dist-info/DESCRIPTION.rst
djangocms_timer-0.1.0.dist-info/RECORD
djangocms_timer-0.1.0.dist-info/metadata.json
