Metadata-Version: 2.0
Name: djangocms-timer
Version: 0.1.0
Summary: django CMS plugin that shows content between specified times
Home-page: https://github.com/nephila/djangocms-timer
Author: Iacopo Spalletti
Author-email: i.spalletti@nephila.it
License: GPLv2+
Keywords: djangocms-timer
Platform: UNKNOWN
Classifier: Development Status :: 2 - Pre-Alpha
Classifier: Framework :: Django
Classifier: Intended Audience :: Developers
Classifier: License :: OSI Approved :: BSD License
Classifier: Natural Language :: English
Classifier: Programming Language :: Python :: 2
Classifier: Programming Language :: Python :: 2.6
Classifier: Programming Language :: Python :: 2.7
Classifier: Programming Language :: Python :: 3
Classifier: Programming Language :: Python :: 3.3
Requires-Dist: django-cms (>=3.0)
